{
    "version": "2025.05.24.060441",
    "description": "A file list program that supports multiple storage, powered by Gin and Solidjs.",
    "homepage": "https://alist.nn.ci",
    "license": "AGPL-3.0-or-later",
    "architecture": {
        "64bit": {
            "url": "https://github.com/AlistGo/alist/releases/download/beta/alist-windows-amd64.zip",
            "hash": "md5:98e7dad32b394bb2e43c5eb5328cc301"
        },
        "32bit": {
            "url": "https://github.com/AlistGo/alist/releases/download/beta/alist-windows-386.zip",
            "hash": "md5:be09150ce25117b38577f0f6bc06a886"
        },
        "arm64": {
            "url": "https://github.com/AlistGo/alist/releases/download/beta/alist-windows-arm64.zip",
            "hash": "d2e58d77f5f204ae76c499716d895b4da0f3c62585f55d7aa3449eb87de59519"
        }
    },
    "bin": [
        [
            "alist.exe",
            "alist",
            "--force-bin-dir"
        ]
    ],
    "persist": [
        "data",
        "log"
    ],
    "checkver": {
        "url": "https://api.github.com/repos/AlistGo/alist/releases/tags/beta",
        "jsonpath": "$.assets[?(@.name == 'alist-windows-amd64.zip')].updated_at",
        "regex": "(\\d+)-(\\d+)-(\\d+)T(\\d+):(\\d+):(\\d+)Z",
        "replace": "${1}.${2}.${3}.${4}${5}${6}"
    },
    "autoupdate": {
        "architecture": {
            "64bit": {
                "url": "https://github.com/AlistGo/alist/releases/download/beta/alist-windows-amd64.zip"
            },
            "32bit": {
                "url": "https://github.com/AlistGo/alist/releases/download/beta/alist-windows-386.zip"
            },
            "arm64": {
                "url": "https://github.com/AlistGo/alist/releases/download/beta/alist-windows-arm64.zip"
            }
        },
        "hash": {
            "url": "$baseurl/md5.txt"
        }
    }
}
