{
    "version": "2025.10.08.005631",
    "description": "An open-source remote desktop application designed for self-hosting, as an alternative to TeamViewer.",
    "homepage": "https://github.com/rustdesk/rustdesk",
    "license": "AGPL-3.0-only",
    "notes": [
        "* Known issue:",
        "  - UAC/Elevation Related : https://rustdesk.com/docs/en/client/windows-portable-elevation/"
    ],
    "architecture": {
        "64bit": {
            "url": "https://github.com/rustdesk/rustdesk/releases/download/nightly/rustdesk-1.4.2-x86_64.msi",
            "hash": "0eb8eb591c6658d393a2c82de3bc3984873cda31c3a4c7ff3b971cd7e246b2ad",
            "extract_dir": "PFiles64\\RustDesk"
        },
        "32bit": {
            "url": "https://github.com/rustdesk/rustdesk/releases/download/nightly/rustdesk-1.4.2-x86-sciter.exe#/RustDesk.exe",
            "hash": "8242372e6eb0ecffe576227d2a12a527ae45ad6164d822d84416d5b3369ca962"
        }
    },
    "shortcuts": [
        [
            "RustDesk.exe",
            "RustDesk"
        ]
    ],
    "checkver": {
        "script": [
            "$api = Invoke-RestMethod 'https://api.github.com/repos/rustdesk/rustdesk/releases/tags/nightly'",
            "foreach ($ass in $api.assets) { ",
            "    if ($ass.name -clike '*-x86_64.msi') { ",
            "        $ass.name + '=====' + (Get-Date $ass.updated_at -Format 'yyyy.MM.dd.HHmmss' -AsUTC)",
            "        break",
            "    } ",
            "}"
        ],
        "regex": "rustdesk-(?<release>[\\d.-]+)-x86_64.msi=====(?<date>.+)",
        "replace": "${date}"
    },
    "autoupdate": {
        "architecture": {
            "64bit": {
                "url": "https://github.com/rustdesk/rustdesk/releases/download/nightly/rustdesk-$matchRelease-x86_64.msi"
            },
            "32bit": {
                "url": "https://github.com/rustdesk/rustdesk/releases/download/nightly/rustdesk-$matchRelease-x86-sciter.exe#/RustDesk.exe"
            }
        }
    }
}
